{
	"room": "Electro Brasil",
	"css": "https://rawgit.com/allanelectrobrasil/ebcustom/master/eb.css",
	"rules": {
            "allowAutorespond":     true,
            "allowAutowoot":        true,
            "allowAutojoin":        false,
            "allowAutograb":        true,
            "allowSmartVote":       true,
            "allowEmotes":          true,
            "allowShowingMehs":     true,
            "forceSmartVote":       false
	},
	"ccc": {
	    "ambassador": "#89be6c !important",
	    "bouncer": "null",
	    "cohost": null,
	    "rdj": null,
	    "host": "#42a5dc",
	    "manager": null,
	    "admin": null,
	    "subscriber": null,
	    "friend": null,
	    "user": null
	},
	"images": {
	    "background": "http://i.imgur.com/q6Jtusl.png",
	    "playback": null,
	    "admin": null,
	    "ambassador": null,
	    "host": null,
	    "cohost": null,
	    "manager": null,
	    "bouncer": null,
	    "rdj": null, 
	    "silversubscriber": null,
	    "subscriber": null
	},
        "emotes": {
	  "tom": "https://i.imgur.com/dLxtSmc.png",
      "xofana": "https://i.imgur.com/cxXlhnC.png",
      "pong": "https://i.imgur.com/q25Hmgj.png",
      "dar": "https://i.imgur.com/EgYOSEy.png",
      "chichi": "https://i.imgur.com/48uSF5V.png",
      "apaki2": "https://i.imgur.com/8ATO3Xy.png",
      "elvis": "https://i.imgur.com/tN1LGVQ.jpg",
      "pequenoigorce": "https://i.imgur.com/vwmObLG.png",
	  "igor": "https://i.imgur.com/vwmObLG.png",
	  "igorce": "https://i.imgur.com/vwmObLG.png",
	  "igorce9": "https://i.imgur.com/vwmObLG.png",
      "chokolat": "https://i.imgur.com/NqcQ85h.png",
      "keini": "https://i.imgur.com/y4hEF0v.png",
      "apaki": "https://i.imgur.com/7rk9I4y.png",
      "mayumi": "https://i.imgur.com/Y7i3bd2.png",
      "space": "https://i.imgur.com/UcT6elY.png",
      "kodek": "https://i.imgur.com/nCAoked.png",
      "nathy": "https://i.imgur.com/OoxKLfR.png",
      "arcadia": "https://i.imgur.com/L6A2yik.png",
      "cleyton": "https://i.imgur.com/Lc3rq1P.jpg",
      "pdp": "https://i.imgur.com/njLHW3I.png",
      "thomas": "https://i.imgur.com/4GqPhVM.png",
      "funkybasic": "https://i.imgur.com/6Lagyue.png",
      "mrline": "https://i.imgur.com/4G2fTI0.png",
      "axl": "https://i.imgur.com/eaYZ3m7.gif",
      "unclesam": "https://i.imgur.com/jkMm5YL.jpg",
      "kappagif": "https://i.imgur.com/ImGltes.gif",
      "dirp": "https://i.imgur.com/ZaC7iBS.jpg",
      "fini": "https://i.imgur.com/L0HbmSv.png",
      "fuckyea": "https://i.imgur.com/rPGedvQ.png",
      "mrbean": "https://i.imgur.com/zGMdKSM.png",
      "varg": "https://i.imgur.com/MR59IZ9.png",
      "ui": "https://i.imgur.com/se9HkCG.png",
      "smoke": "https://i.imgur.com/OnNLzcA.gif",
      "fatality": "https://i.imgur.com/QDiLcwq.gif",
      "okay": "https://i.imgur.com/BpQWgTs.gif",
      "notsureif": "https://i.imgur.com/4jPyRG2.png",
      "lennygif": "https://i.imgur.com/OSdFEcj.gif",
      "problem": "https://i.imgur.com/2B7A7ZK.png",
      "gay": "https://i.imgur.com/zXpqTDT.gif",
      "facepalmgif": "https://i.imgur.com/Jovv7R6.gif",
      "cage": "https://i.imgur.com/MRbkpXW.gif",
      "mehmute": "https://i.imgur.com/t6SN0IE.png",
      "gandalf": "https://i.imgur.com/lnhZFB6.gif",
      "legolas": "https://i.imgur.com/oZcyeUz.gif",
      "sax": "https://i.imgur.com/FCrmC79.gif",
      "batpika": "https://i.imgur.com/0csyj4e.png",
      "goodnight": "https://i.imgur.com/53sUCe5.gif",
      "genius": "https://i.imgur.com/FRUXfYj.png",
      "bitch": "https://i.imgur.com/HIn3Z2J.gif",
      "hunter": "https://i.imgur.com/Anc5bAa.jpg",
      "frozen": "https://i.imgur.com/OrBbpKg.gif",
      "sad": "https://i.imgur.com/z8wyK0s.gif",
      "killit": "https://i.imgur.com/UNMXgJr.gif",
      "hiding": "https://i.imgur.com/xJx2tpg.gif",
      "darkness": "https://i.imgur.com/xQLMoma.jpg",
      "sanicgif": "https://i.imgur.com/52yzQ5I.gif",
      "haha": "https://i.imgur.com/yl2fr1z.gif",
      "weed": "https://i.imgur.com/OwunEuJ.gif",
      "damn": "https://i.imgur.com/muNvl6b.gif",
      "feels": "https://i.imgur.com/7pjGsQX.jpg",
      "feels2": "https://i.imgur.com/huHTzIU.jpg",
      "feels3": "https://i.imgur.com/Px8fLIR.jpg",
      "feels4": "https://i.imgur.com/8nDfxyd.jpg",
      "feels5": "https://i.imgur.com/v4LUafF.jpg",
      "feels6": "https://i.imgur.com/rJxSX8W.jpg",
      "feels7": "https://i.imgur.com/ZBfVjRZ.jpg",
      "feels8": "https://i.imgur.com/V9cq9BT.jpg",
      "feels9": "https://i.imgur.com/pgP3EjB.jpg",
      "feelsbad": "https://i.imgur.com/Io4Zvs3.jpg",
      "feelsgif": "https://i.imgur.com/GiOEYlD.gif",
      "wank": "httpS://i.imgur.com/L883Rhz.gif",
      "popcorn": "https://i.imgur.com/zQSiTYG.gif",
      "king": "https://i.imgur.com/sfFsio3.png",
      "shot": "https://i.imgur.com/WpsqBvo.gif",
      "ponny": "https://i.imgur.com/W4gomLB.gif",
      "skrill": "https://i.imgur.com/uV7Hxbc.gif",
      "thebug": "https://i.imgur.com/bmmX86O.gif",
      "nichi": "https://i.imgur.com/TguLQ6K.jpg",
      "bob": "https://i.imgur.com/yejRBgc.gif",
      "salobrena": "https://i.imgur.com/rmjOxgx.png",
      "joseph": "https://i.imgur.com/cyadKv2.jpg",
      "joseph2": "https://i.imgur.com/RKFaPo3.jpg",
      "god": "https://i.imgur.com/YfG5u6F.gif",
      "nelson": "https://i.imgur.com/8be9xVy.png",
      "babby": "https://i.imgur.com/u1O9yyD.png",
      "alpaca": "https://i.imgur.com/cLsx49C.gif",
      "mlg": "https://i.imgur.com/vKXhX8b.gif",
      "nyan": "https://i.imgur.com/zkYnA9D.gif",
      "picard": "https://i.imgur.com/CJSAWol.png",
      "watislove": "https://i.imgur.com/hpViBhw.gif",
      "boromir": "https://i.imgur.com/s4c6m3f.jpg",
      "highguy": "https://i.imgur.com/0XXi7aF.png",
      "highguy2": "https://i.imgur.com/B6wKunc.png",
      "sexyhighguy": "https://i.imgur.com/ZvpeZVv.png",
      "ponny2": "https://i.imgur.com/KOADBQU.gif",
      "fusion": "https://i.imgur.com/XcdvTtu.gif",
      "bait": "https://i.imgur.com/AyHjulQ.gif",
      "avatar": "https://i.imgur.com/P5ZrmRP.gif",
      "heman": "https://i.imgur.com/7UywzY4.gif",
      "guide": "https://i.imgur.com/yAdkMpu.png",
      "bestcry": "https://i.imgur.com/OO1gNKi.gif",
      "lastkill": "https://i.imgur.com/rUCzGSf.jpg",
      "fishbang": "https://i.imgur.com/BC9F1qV.gif",
      "beavis": "https://i.imgur.com/2j9HTyt.gif",
      "doge": "https://i.imgur.com/9rQZdFj.jpg",
      "ivan": "https://i.imgur.com/vI9t0ZC.jpg",
      "vibe": "https://i.imgur.com/w0xUqkt.gif",
      "bunchie": "https://i.imgur.com/6diM286.gif",
      "oh": "https://i.imgur.com/OZRWuwJ.gif",
      "sanic": "https://i.imgur.com/er4UCZz.png",
      "tutstuts": "https://dl.dropboxusercontent.com/s/rnz9u2pmuqjsms1/tutstuts.gif",
      "molester": "https://dl.dropboxusercontent.com/s/lmtzhdgjztcb18m/molester.gif",
      "smiile": "https://i.imgur.com/uM57U6I.gif",
      "michael": "https://dl.dropboxusercontent.com/s/zlqyshqmfnru8ko/michael.gif",
      "will": "https://i.imgur.com/666sGQo.gif",
      "yaranaika": "https://i.imgur.com/YeRJUkr.jpg",
      "surprise": "https://i.imgur.com/bdP6uzI.gif",
      "wonka": "https://i.imgur.com/TfsmQ3Z.jpg",
      "kim": "https://dl.dropboxusercontent.com/s/imaxuzsen111y3j/aplauso.gif",
      "hhoo": "https://i.imgur.com/jGyKtjc.png",
      "hhoogif": "https://i.imgur.com/FOrMJt3.gif",
      "feargif": "https://i.imgur.com/w7uz0vw.gif",
      "wtfgif": "https://dl.dropboxusercontent.com/s/ky65dm617j7nkv2/wtf.gif",
      "trap": "https://i.imgur.com/U2UGB8D.png",
      "jesuspalm": "https://i.imgur.com/tx0DZfO.jpg",
      "hitler": "https://dl.dropboxusercontent.com/s/51kbxw8lcbv69b2/hitler.gif",
      "blarg": "https://i.imgur.com/J5VW4ia.gif",
      "donvoo": "https://i.imgur.com/mEQIRCb.gif",
      "quit": "https://i.imgur.com/wTmQGTG.png",
      "jhow": "https://i.imgur.com/SlpIptB.png",
      "ook": "https://i.imgur.com/dp4Cnid.png",
      "noob": "https://i.imgur.com/hxJqZ1N.png",
      "lol": "https://i.imgur.com/eJXx4er.png",
      "you": "https://i.imgur.com/X8NFKlX.png",
      "omg": "https://i.imgur.com/0o9WEjA.png",
      "wtf": "https://i.imgur.com/xLHzV4T.png",
      "ranger1": "https://i.imgur.com/usaTVmf.png",
      "ranger2": "https://i.imgur.com/D1qBRht.png",
      "ranger3": "https://i.imgur.com/ezF3UWH.png",
      "ranger4": "https://i.imgur.com/MdgA9D7.png",
      "ranger5": "https://i.imgur.com/RuvO5WF.png",
      "mightygif": "https://i.imgur.com/kzRyNAW.gif",
      "lanna": "https://i.imgur.com/BSyp4pV.png",
      "ranger6": "https://i.imgur.com/gAY6ihA.png",
      "doze": "https://i.imgur.com/i0X4JGS.png;",
      "cj": "https://i.imgur.com/32Nnqmc.png",
      "pei": "https://i.imgur.com/PsxiB3u.gif",
      "banger": "https://i.imgur.com/1OSsdHD.gif",
      "banger2": "https://i.imgur.com/LwcEmSG.gif",
      "banger3": "https://i.imgur.com/5cezcWG.gif",
      "banger4": "https://i.imgur.com/MrtbDUW.gif",
      "banger5": "https://i.imgur.com/sQ9MBhG.gif",
      "banger6": "https://i.imgur.com/kX8eV8y.gif",
      "under": "https://i.imgur.com/7qMVolj.gif",
      "disposta": "https://imgur.com/7Xr6mJ5.jpg",
      "marcelo": "https://i.imgur.com/KJ7VuYX.jpg",
      "demente": "https://i.imgur.com/hcFHm28.gif",
      "naruto": "https://i.imgur.com/bkHjNVp.gif",
      "tacerto": "https://i.imgur.com/6dBnnKB.gif",
      "nerdpalm": "https://i.imgur.com/nahfbMb.jpg",
      "foda.se": "https://i.imgur.com/Ju4rLQA.jpg",
      "foda-se3": "https://i.imgur.com/0EfQWMN.jpg",
      "foda-se4": "https://i.imgur.com/X7HEXSX.png",
      "sefoda": "https://i.imgur.com/IDHE3Ve.gif",
      "sefoda2": "https://i.imgur.com/igDZYOt.gif",
      "sefoda3": "https://i.imgur.com/WcV2IVL.gif",
      "diploma": "https://i.imgur.com/aNySCx2.jpg",
      "bemloco": "https://i.imgur.com/YQiKFHx.jpg",
      "qponto": "https://imgur.com/4NdIVTN.jpg",
      "uehue": "https://i.imgur.com/Q1bh0mL.jpg",
      "lennyface": "https://i.imgur.com/g4zRJ9C.jpg",
      "léostronda": "https://i.imgur.com/tsv7zX4.png",
      "ozzydeia": "https://i.imgur.com/YCGImPN.jpg",
      "huera": "https://i.imgur.com/eGdbSgO.jpg",
      "jachega": "https://i.imgur.com/aTmTdas.png",
      "pistola": "https://i.imgur.com/Z9to5Nl.png",
      "mcq": "https://i.imgur.com/X5R9Orx.jpg",
      "feelsmj": "https://i.imgur.com/i0cx6UN.jpg",
      "bixao": "https://i.imgur.com/Yu59ztU.png",
      "feels1": "https://i.imgur.com/rmj7p6s.jpg",
      "hu3br": "https://i.imgur.com/lM5EMUZ.jpg",
      "tainá": "https://i.imgur.com/umm8KTs.jpg",
      "feels10": "https://i.imgur.com/FFFOcFP.jpg",
      "vaitomar": "https://i.imgur.com/Ipmcfx2.jpg",
      "idai": "https://i.imgur.com/OgHQCry.jpg",
      "hmm2": "https://i.imgur.com/4PzgMep.jpg",
      "feelsnigga": "https://i.imgur.com/OnzQsC7.jpg",
      "feelsbro": "https://i.imgur.com/pWzA0Fi.gif",
      "pepe": "https://i.imgur.com/ZNz8T3V.jpg",
      "pepe2": "https://i.imgur.com/arwt3ny.jpg",
      "rarepepe": "https://i.imgur.com/w2fwciR.gif",
      "q2": "https://i.imgur.com/df4twj2.png",
      "tiririca": "https://i.imgur.com/SOZ6R1O.jpg",
      "anel": "https://i.imgur.com/XoEFSNa.jpg",
      "apunhala": "https://i.imgur.com/nlscXR7.gif",
      "lhama": "https://i.imgur.com/uUNdVs7.gif",
      "relaxha": "https://i.imgur.com/XkhbLVL.gif",
      "pinto": "https://i.imgur.com/M4Fbzrl.jpg",
      "danada": "https://i.imgur.com/jJotain.png",
      "acabou": "https://imgur.com/vfN1hJq.jpg",
      "dilma": "https://i.imgur.com/emL3hBV.png",
      "dilma2": "https://i.imgur.com/usdVJb3.jpg",
      "dilma3": "https://i.imgur.com/7eGFqGJ.jpg",
      "dilma4": "https://imgur.com/FdWAely.jpg",
      "dilmapalm": "https://i.imgur.com/Ub19Cm1.jpg",
      "wills1": "https://i.imgur.com/bB7kIzm.png",
      "wills2": "https://i.imgur.com/rUyDySG.png",
      "wills3": "https://i.imgur.com/5nIIgVS.jpg",
      "maigode": "https://i.imgur.com/6kZ4Br6.jpg",
      "maigode2": "https://i.imgur.com/n79SjXm.jpg",
      "nao1": "https://i.imgur.com/30Yl6Hk.jpg",
      "vergonha": "https://i.imgur.com/XF5PEKF.png",
      "seriouslee": "https://i.imgur.com/54fKIrl.jpg",
      "em": "https://i.imgur.com/qlMQyza.jpg",
      "facacrack": "https://i.imgur.com/loRLhnz.jpg",
      "moitai": "https://i.imgur.com/X379iNh.png",
      "nossa": "https://i.imgur.com/FgrAWii.jpg",
      "nudes": "https://i.imgur.com/pvUWCt7.jpg",
      "queviaje": "https://i.imgur.com/1Pp17HT.jpg",
      "toma2": "https://i.imgur.com/Tgen56Z.jpg",
      "quelixo": "https://i.imgur.com/g9IKzd1.jpg",
      "strondou": "https://i.imgur.com/18jBXx7.jpg",
      "sefuder": "https://i.imgur.com/34K5mb7.jpg",
      "myers": "https://i.imgur.com/yR4Vcim.gif",
      "jason": "https://i.imgur.com/OrxWC9g.gif",
      "terror": "https://i.imgur.com/mLInq4V.gif",
      "terror2": "https://i.imgur.com/dE0gx7k.gif",
      "terror3": "https://i.imgur.com/uBYvuGi.gif",
      "terror4": "https://i.imgur.com/fb9caMi.gif",
      "rasengao": "https://i.imgur.com/COlkcUQ.jpg",
      "penes": "https://i.imgur.com/ypzUakJ.png",
      "penes2": "https://i.imgur.com/b3Vv0RI.png",
      "hu3": "https://i.imgur.com/wiQ0cyG.gif",
      "vai": "https://i.imgur.com/rmxse7j.png",
      "nãosei": "https://i.imgur.com/QoPAHYd.png",
      "dlç3": "https://i.imgur.com/e445lXo.png",
      "berg": "https://i.imgur.com/ZGBr0D1.png",
      "funky": "https://i.imgur.com/SB0wfqT.jpg",
      "desgraça": "https://i.imgur.com/erZNL5n.png",
      "caue": "https://i.imgur.com/cRZDj11.jpg",
      "milgrau": "https://i.imgur.com/xDZbwok.png",
      "foda-se": "https://i.imgur.com/8pBXLn7.gif",
      "foda-se2": "https://i.imgur.com/bCYVoEx.jpg",
      "close1": "https://i.imgur.com/SGzBFTp.gif",
      "close2": "https://i.imgur.com/Laq6SCL.gif",
      "palhaço": "https://i.imgur.com/k6D8MdT.png",
      "victor": "https://i.imgur.com/wOuX2zo.jpg",
      "cleyton2": "https://i.imgur.com/LnEa0PR.gif",
      "pdp2": "https://i.imgur.com/AVBHM0F.png",
      "bigboss": "https://i.imgur.com/lsbGomk.jpg",
      "vinny": "https://i.imgur.com/AhOBaXj.png",
      "toma": "https://i.imgur.com/NFk9jbx.gif?1",
      "uau": "https://i.imgur.com/InFJRi3.gif",
      "burraum": "https://i.imgur.com/gV9KPyI.gif",
      "ibagens": "https://i.imgur.com/bl0tfBN.jpg",
      "nentendi": "https://i.imgur.com/AcN6tOG.gif",
      "dollynho": "https://i.imgur.com/66UwC9Q.jpg",
      "madruga": "https://i.imgur.com/OvDq257.gif",
      "sim": "https://i.imgur.com/NL9o8ng.gif",
      "naocreio": "https://i.imgur.com/CNSxy3B.jpg",
      "mandanude": "https://i.imgur.com/PTYLcye.png",
      "zoeira": "https://i.imgur.com/zVFnkQU.png",
      "morre": "https://i.imgur.com/B100qjp.gif",
      "cachoeira": "https://i.imgur.com/M0OKa03.png",
      "popeye": "https://i.imgur.com/O5nQ086.gif",
      "diney": "https://i.imgur.com/wPY0bOk.gif",
      "coração": "https://i.imgur.com/stGYuBH.jpg",
      "dribe4": "https://i.imgur.com/CjizyLK.jpg",
      "ficouoh": "https://i.imgur.com/h1ZFm2P.jpg",
      "dlç5": "https://i.imgur.com/SnIVw8Q.jpg",
      "oxe": "https://i.imgur.com/6m4EzlB.gif",
      "numsei": "https://i.imgur.com/Hh0RnJH.gif",
      "idiota": "https://i.imgur.com/ocsGCQv.gif",
      "istudu": "https://i.imgur.com/XuJbgWk.gif",
      "linteressa": "https://i.imgur.com/xhCO25z.gif",
      "dazero": "https://i.imgur.com/88ADPRt.png",
      "ésim": "https://i.imgur.com/tALpIWp.jpg",
      "infarto": "https://i.imgur.com/3hvzwln.jpg",
      "chola": "https://i.imgur.com/UqwOG4q.gif",
      "chora2": "https://i.imgur.com/lc3SU60.gif",
      "emsm": "https://i.imgur.com/aDhjPXx.jpg",
      "destruidora": "https://i.imgur.com/d6jxPLi.gif",
      "monalicia": "https://i.imgur.com/35Jrx9b.png",
      "r10": "https://i.imgur.com/yXY2KHX.jpg",
      "r10secret": "https://i.imgur.com/o0Ha07A.jpg",
      "freestep": "https://i.imgur.com/bfDKHgM.gif",
      "morrison": "https://i.imgur.com/6g3PA6d.gif",
      "burro": "https://i.imgur.com/qle8kwP.gif",
      "dlc": "https://i.imgur.com/GIfMPSz.jpg",
      "caetano": "https://i.imgur.com/4zuh99t.gif",
      "prerigo": "https://i.imgur.com/rdzc9ca.png",
      "suicídio": "https://i.imgur.com/SpsBBF8.jpg",
      "away": "https://i.imgur.com/RzY8ev4.gif",
      "saxguy": "https://i.imgur.com/86nV3Ms.gif",
      "tapa": "https://i.imgur.com/p8bZveT.png",
      "zoeiro": "https://i.imgur.com/jBr1NaT.jpg",
      ".v.": "https://i.imgur.com/C79uctl.gif",
      "graça": "https://i.imgur.com/4f7LR3B.jpg",
      "bravo": "https://i.imgur.com/H37xWtB.gif",
      "café": "https://i.imgur.com/lMWBD0j.png",
      "deselegante2": "https://i.imgur.com/mvzHy3M.png",
      "brendan": "https://i.imgur.com/4GMdSLZ.gif",
      "punheteiro": "https://i.imgur.com/OVayNxL.png",
      "fodace": "https://i.imgur.com/mbHJvoR.gif",
      "dopado": "https://i.imgur.com/DQI1o7D.gif",
      "observo": "https://i.imgur.com/XgDXpu5.gif",
      "chega": "https://i.imgur.com/chizmUF.gif",
      "deselegante": "https://i.imgur.com/H8PJvmc.png",
      "cu": "https://i.imgur.com/DGaDOyK.gif",
      "vaifodase": "https://i.imgur.com/b3zJklr.jpg",
      "carsampley": "https://i.imgur.com/c1lqPLc.gif",
      "olha": "https://i.imgur.com/5lKVDdL.png",
      "100%": "https://i.imgur.com/nhz07pH.jpg",
      "kiko": "https://i.imgur.com/yp0iKfs.gif",
      "faustek": "https://i.imgur.com/Ciet3Lh.jpg",
      "poder": "https://i.imgur.com/DxHp6Ey.jpg",
      "chora": "https://i.imgur.com/hMZaAIg.gif",
      "cachorra": "https://i.imgur.com/MpFRqto.jpg",
      "baforada": "https://i.imgur.com/1ROrlOJ.jpg",
      "ronaldinho": "https://i.imgur.com/fitbnt9.jpg",
      "piruleta2": "https://i.imgur.com/BOZZemI.jpg",
      "dikarada": "https://i.imgur.com/cWOiX1V.jpg",
      "espertalhão": "https://i.imgur.com/ToQAlgf.jpg",
      "hipotenusa": "https://i.imgur.com/q8bjQQ0.jpg",
      "lençóis": "https://i.imgur.com/E6TwxMO.jpg",
      "mordida": "https://i.imgur.com/Xg3UCOz.jpg",
      "naburo": "https://i.imgur.com/EFCv0C3.jpg",
      "paladino": "https://i.imgur.com/qgxzYXU.jpg",
      "piru": "https://i.imgur.com/Huuxz9x.jpg",
      "bopiti": "https://i.imgur.com/DfoiG3t.jpg",
      "madrugada": "https://i.imgur.com/ABFs2gU.jpg",
      "pergunto": "https://i.imgur.com/nz9q8oa.jpg",
      "picapau": "https://i.imgur.com/EpfCXRM.png",
      "ler": "https://i.imgur.com/dP3k6pR.jpg",
      "faleceu": "https://i.imgur.com/vZE62y1.jpg",
      "demencia": "https://i.imgur.com/OUiQqjM.jpg",
      "tesão": "https://i.imgur.com/I0NsPEe.jpg",
      "ovo": "https://i.imgur.com/MojsPPc.gif",
      "mizeravi": "https://i.imgur.com/4ILWtwV.png",
      "legal": "https://i.imgur.com/NAvDJFl.jpg",
      "recalque": "https://i.imgur.com/BvOMvP9.gif",
      "virj": "https://i.imgur.com/WDeHtAa.png",
      "hjn": "https://i.imgur.com/SoZkcP3.jpg",
      "negócio": "https://i.imgur.com/rPIhhjM.gif",
      "tomarnocu": "https://i.imgur.com/CBcOPoj.jpg",
      "calmafera": "https://i.imgur.com/ZvPsaZ7.jpg",
      "ai": "https://i.imgur.com/9nPt2Dk.gif",
      "rapariga": "https://i.imgur.com/puyTsuO.jpg",
      "bosta": "https://i.imgur.com/cukzX3j.png",
      "naopodese": "https://i.imgur.com/q4nxSjA.gif",
      "providencia": "https://i.imgur.com/HmB60BT.png",
      "crackante": "https://i.imgur.com/G5qqjBF.png",
      "putavida": "https://i.imgur.com/dhnwM5I.gif",
      "travadão2": "https://i.imgur.com/Li46Bhh.jpg",
      "viadagem": "https://i.imgur.com/wXmhCyx.png",
      "costinha": "https://i.imgur.com/K4x7UqI.gif",
      "rosque": "https://i.imgur.com/3bs2prg.jpg",
      "sexo": "https://i.imgur.com/SXXcqnB.gif",
      "hmm": "https://i.imgur.com/ofTagdg.gif",
      "émermo": "https://i.imgur.com/Ps0U7pW.gif",
      "yudi": "https://i.imgur.com/cIObhMl.jpg",
      "sefodeu": "https://i.imgur.com/S51VdIi.jpg",
      "caimbra": "https://i.imgur.com/L4idMA8.gif",
      "rica": "https://i.imgur.com/hzqgxR6.gif",
      "gente": "https://i.imgur.com/ORjnzfn.jpg",
      "demacol": "https://i.imgur.com/Bdi1ADi.jpg",
      "chorei": "https://i.imgur.com/hFFM8Pn.jpg",
      "brasil": "https://i.imgur.com/o43kLTx.jpg",
      "viadãobonito": "https://i.imgur.com/zkO4uuS.jpg",
      "bengay": "https://i.imgur.com/RbmI3ot.jpg",
      "viadão": "https://i.imgur.com/t1YAxJp.jpg",
      "parede": "https://i.imgur.com/deJHDnl.gif",
      "pocaralho": "https://i.imgur.com/NVgxpMW.jpg",
      "émentira": "https://i.imgur.com/JQEmF2m.gif",
      "emsme": "https://i.imgur.com/pfQVT5U.jpg",
      "sujou": "https://i.imgur.com/hd29JPY.gif",
      "chora3": "https://i.imgur.com/EtSFqhT.gif",
      "empolgante": "https://i.imgur.com/R3HHVD2.jpg",
      "dribe3": "https://i.imgur.com/57FtsgX.jpg",
      "dribe2": "https://i.imgur.com/aUkbohX.jpg",
      "fodase": "https://i.imgur.com/j1cSxm0.jpg",
      "pclixo": "https://i.imgur.com/aVrNvoO.gif",
      "brinks": "https://i.imgur.com/DkQGbjs.jpg",
      "talento": "https://i.imgur.com/qBikFj6.gif",
      "util": "https://i.imgur.com/InUkCys.gif",
      "gato": "https://i.imgur.com/wRI10nK.gif",
      "xablau": "https://i.imgur.com/uEHQSrA.gif",
      "nadar": "https://i.imgur.com/t3tpnOf.gif",
      "psg": "https://i.imgur.com/7DGHT1Z.jpg",
      "fofão": "https://i.imgur.com/8Mq3tPR.gif",
      "rei": "https://i.imgur.com/7Nyigun.jpg",
      "quente": "https://i.imgur.com/VU5nU6H.jpg",
      "exu": "https://i.imgur.com/V4DsMxC.png",
      "pesquisa": "https://i.imgur.com/hlOb17t.jpg",
      "piruleta": "https://i.imgur.com/O9DIs16.gif",
      "jooj": "https://i.imgur.com/JP8UacY.gif",
      "desver": "https://i.imgur.com/s5Q7YVs.jpg",
      "matador": "https://i.imgur.com/YUkN7Vr.png",
      "pão": "https://i.imgur.com/7TNXE0O.jpg",
      "bilada": "https://i.imgur.com/P8atE5v.png",
      "chico": "https://i.imgur.com/jTncWAZ.png",
      "aiai": "https://i.imgur.com/ET7tvuC.gif",
      "vaicry": "https://i.imgur.com/05uFYdE.png",
      "cryisfree": "https://i.imgur.com/ZHj6lkY.png",
      "tacry": "https://i.imgur.com/WrYcJtP.jpg",
      "treta": "https://i.imgur.com/3XiQPSH.gif",
      "loko": "https://i.imgur.com/WgHIVeP.gif",
      "nigga": "https://i.imgur.com/4OcxTYV.gif",
      "jailson": "https://i.imgur.com/dVthkoQ.gif",
      "jailson2": "https://i.imgur.com/sLlX5B2.jpg",
      "jailson3": "https://i.imgur.com/XfJNTVs.jpg",
      "jailson4": "https://i.imgur.com/G08Oq6x.gif",
      "cazalbe": "https://dl.dropboxusercontent.com/s/cmdveivyf883e23/cazalbe.gif",
      "cazalbe2": "https://i.imgur.com/15XzVbp.jpg",
      "nao": "https://i.imgur.com/XGAXb3O.png",
      "nadave": "https://i.imgur.com/IydoxRH.png",
      "baidu": "https://i.imgur.com/nbdh0aA.jpg",
      "dribe": "https://i.imgur.com/IfVOE3J.jpg",
      "mentira": "https://i.imgur.com/qeZB5PW.jpg",
      "papaco": "https://i.imgur.com/OKJJJps.jpg",
      "tainha": "https://i.imgur.com/zbcDRxQ.jpg",
      "travadão": "https://i.imgur.com/MDxiEbz.jpg",
      "papaco2": "https://i.imgur.com/8R1TWc0.jpg",
      "erou": "https://i.imgur.com/4wrakbp.jpg",
      "euquis": "https://i.imgur.com/iZdZPPd.jpg",
      "desu": "https://i.imgur.com/Z5cg89l.png",
      "masc": "https://i.imgur.com/O49ugVB.png",
      "parca": "https://i.imgur.com/AsQFN9e.png",
      "dibre": "https://i.imgur.com/oKyrjOv.png",
      "dibre1": "https://i.imgur.com/UZQjGlG.png",
      "marina": "https://i.imgur.com/UHRpp4d.png",
      "meobrigue": "https://i.imgur.com/HrfUfMS.png",
      "taquerendo": "https://dl.dropboxusercontent.com/s/q9i6gdl6f8ylepi/seicome.gif",
      "agredi": "https://i.imgur.com/JB7zmTi.png",
      "diva": "https://dl.dropboxusercontent.com/s/ordgqct09npvogd/diva.gif",
      "monstro": "https://i.imgur.com/1pIrVfq.png",
      "monstrogif": "https://i.imgur.com/15hqUd0.gif",
      "dança": "https://i.imgur.com/E3dkL3t.gif",
      "dlç": "https://i.imgur.com/OgwkZzo.png",
      "dlç2": "https://i.imgur.com/JZ8VKWc.jpg",
      "dlç4": "https://i.imgur.com/EkOBJyT.png",
      "dlçgif": "https://i.imgur.com/1cU7mt3.gif",
      "dragão": "https://i.imgur.com/b79bIsm.png",
      "parabains": "https://i.imgur.com/biIoQe8.jpg",
      "puto": "https://i.imgur.com/v9h01r1.png",
      "numintendi": "https://i.imgur.com/pB51GvI.jpg",
      "corre": "https://i.imgur.com/LrT4c1X.jpg",
      "dinossauro": "https://i.imgur.com/T73QENt.png",
      "dinossauro2": "https://i.imgur.com/0nk9NBf.gif",
      "dinossauro3": "https://i.imgur.com/jD2sDdm.gif",
      "fafa": "https://i.imgur.com/m8ZopBV.gif",
      "oco": "https://i.imgur.com/QSBygqu.png",
      "oco2": "https://i.imgur.com/xOX01k3.jpg",
      "pikachurusso": "https://i.imgur.com/hxhBmOG.jpg",
      "drift": "https://i.imgur.com/M7TtL53.gif",
      "dança2": "https://i.imgur.com/nre0Ptz.gif",
      "dança3": "https://i.imgur.com/rXviL4y.gif",
      "dança4": "https://i.imgur.com/sekxiqi.gif",
      "dança5": "http://i.imgur.com/nU6lsS6.gif",
      "dança6": "http://i.imgur.com/DHYAAuT.gif",
      "dança7": "http://i.imgur.com/UXwRBoA.gif",
      "dança8": "http://i.imgur.com/bFsRZcC.gif",
      "dança9": "http://i.imgur.com/H1Wwc0l.gif",
      "sai": "https://i.imgur.com/I80DvSW.png",
      "ban": "https://i.imgur.com/GqRd92T.jpg",
      "okne": "https://i.imgur.com/VkktMNz.gif",
      "barcelona": "https://i.imgur.com/OXc6mzV.png",
      "sp": "https://i.imgur.com/gSKtVby.png",
      "cruzeiro": "https://i.imgur.com/822pXUd.png",
      "santos": "https://i.imgur.com/MHvxHE3.png",
      "realmadrid": "https://i.imgur.com/Qjk3CHM.png",
      "palmeiras": "https://i.imgur.com/nXnIgUg.png",
      "inter": "https://i.imgur.com/1CAyN4A.png",
      "flamengo": "https://i.imgur.com/U8bzkTC.png",
      "gremio": "https://i.imgur.com/RIbNpmy.png",
      "corinthians": "https://i.imgur.com/VRIe1j5.png",
      "afrojack": "https://i.imgur.com/ZTL9rtk.png",
      "arminvanbuuren": "https://i.imgur.com/1gi73aE.png",
      "avicii": "https://i.imgur.com/Y7jwkMz.png",
      "bassnation": "https://i.imgur.com/GYHVvIX.png",
      "calvinharris": "https://i.imgur.com/oCGqAIz.png",
      "deadmau5": "https://i.imgur.com/pM3id2o.png",
      "dondiablo": "https://i.imgur.com/ks45L1M.png",
      "edmcity": "https://i.imgur.com/xeppKAf.png",
      "hardwell": "https://i.imgur.com/vbovXXJ.png",
      "kdrew": "https://i.imgur.com/aNq3yFr.png",
      "knifeparty": "https://i.imgur.com/XTiGAbN.png",
      "krewella": "https://i.imgur.com/Bmh536K.png",
      "martingarrix": "https://i.imgur.com/uFPUJbD.png",
      "ncs": "https://i.imgur.com/DCp0j66.png",
      "nervo": "https://i.imgur.com/Bl4fA7p.png",
      "nickyromero": "https://i.imgur.com/Y2M7C5Y.png",
      "davidguetta": "https://i.imgur.com/YG3L9Zn.png",
      "plugdj": "https://i.imgur.com/e5ZTfvj.png",
      "proximity": "https://i.imgur.com/QSdXIPY.png",
      "rehab": "https://i.imgur.com/0IXROCz.png",
      "showtek": "https://i.imgur.com/Sky8x4t.png",
      "skrillex": "https://i.imgur.com/FeWO8PB.png",
      "steveaoki": "https://i.imgur.com/V2DKyGR.png",
      "prodigy": "https://i.imgur.com/aTK722r.png",
      "tiesto": "https://i.imgur.com/oD4IarB.png",
      "trapcity": "https://i.imgur.com/Z2cX62i.png",
      "virtualriot": "https://i.imgur.com/b57tQFx.png",
      "zedd": "https://i.imgur.com/6aJ09Bl.png",
      "zomboy": "https://i.imgur.com/UHNZvFl.png",
      "gaga": "https://i.imgur.com/B9t4plI.png",
      "gaga2": "http://i.imgur.com/mOCekFW.gif",
      "gaga3": "http://i.imgur.com/3rNMvKB.gif",
      "passenger": "https://i.imgur.com/C1lxN54.png",
      "raego": "https://i.imgur.com/MWXHels.png",
      "top": "http://i.imgur.com/2slxGiv.gif",
      "banks": "http://i.imgur.com/iK54nib.gif",
      "urach1": "http://i.imgur.com/iBpZtyW.gif",
      "gret1": "http://i.imgur.com/G97NrN8.gif",
      "gret2": "http://i.imgur.com/SyQCRc3.gif",
      "gret3": "http://i.imgur.com/6AWQDc7.gif",
      "gret4": "http://i.imgur.com/Cl4nWCa.gif",
      "gret5": "http://cdn.playbuzz.com/cdn/56b78199-8382-4564-9414-3399b0ff1c7a/654c88e4-24c0-4cbb-b84f-48be6d33658c.gif",
      "gret6": "https://lh3.ggpht.com/-o_6w2lbLk04/UsRDkePZjbI/AAAAAAAAJps/Q3ISI-_ATR4/s0/gret3.gif",
      "gret7": "http://www.ahmanolo.com.br/wp-content/uploads/gretcry.gif",
      "gret8": "https://i.imgur.com/SPtpXq5.gif",
      "gret9": "https://lh5.googleusercontent.com/-SwCT88OvG9g/VRYYZmhqkeI/AAAAAAAAAgg/0CAxKkkvQ6c/s122-p/MACONHETC.gif",
      "gret10": "https://lh5.ggpht.com/-7zCplGE7jO4/Uq4PDPruHhI/AAAAAAAAG-A/Bc3ZyG9O_tY/s132/2.gif",
      "gret11": "http://33.media.tumblr.com/9cd887ba088288825213cef9c47b7dfb/tumblr_nesk2aQD4k1u15syro1_250.gif",
      "meudeus": "http://i.imgur.com/dY8uXcV.gif",
      "brit1": "http://i.imgur.com/xZJpGoJ.gif",
      "brit2": "http://i.imgur.com/XYmhRZ5.gif",
      "xtina": "http://i.imgur.com/hvE24WC.gif",
      "vinhado": "http://i.imgur.com/MrpFgrY.gif",
      "vinhado2": "http://i.imgur.com/CmJYjEw.gif",
      "tchau": "http://i.imgur.com/bqjLzLB.gif",
      "riri": "http://i.imgur.com/zdhVM1l.gif",
      "aline1": "http://i.imgur.com/QM9KyuO.gif",
      "aline2": "http://i.imgur.com/7uxnjCa.gif",
      "aline3": "http://i.imgur.com/iduad7p.gif",
      "bbb": "http://i.imgur.com/bvIuTVZ.gif",
      "ines1": "http://i.imgur.com/DqH4G9p.gif",
      "ines2": "http://i.imgur.com/rHw0ZKG.gif",
      "ban": "http://i.imgur.com/suK1BPl.gif",
      "ban2": "http://i.imgur.com/lF6KT0i.gif",
      "ban3": "http://i.imgur.com/pscygbw.gif",
      "gloria": "http://i.imgur.com/rfstxUC.gif",
      "gloria2": "http://i.imgur.com/9Kd2DI5.gif",
      "trans1": "http://i.imgur.com/yhgmUft.png",
      "trans2": "http://i.imgur.com/LbZ2lWu.png",
      "curtir": "http://i.imgur.com/nk4C1tw.gif",
      "cryy": "http://i.imgur.com/uuq4crC.gif",
      "sitio": "http://image.prntscr.com/image/e419172c09634f2c874ac5792dc894a1.png",
      "lana": "http://image.prntscr.com/image/8171dbd7ced4402ab4717ad002f5be0f.png",
      "hino": "http://i.imgur.com/sued5LA.gif",
      "feelsgret1": "http://i.imgur.com/SyQCRc3.gif",
      "feelsgret2": "http://i.imgur.com/ewdEqK9.gif",
      "feelsgret3": "http://i.imgur.com/YG2JIcQ.gif",
      "feelsgret4": "http://i.imgur.com/YUGT9oV.gif",
      "otimo": "https://i.imgur.com/lCvXysf.gif"
        }
      
      
      


}
